colordetect/__init__.py
colordetect/col_share.py
colordetect/color_detect.py
colordetect/video_color_detect.py
tests/__init__.py
tests/conftest.py
tests/test_functional.py
tests/test_unit.py
ColorDetect-1.6.3.dist-info/LICENSE
ColorDetect-1.6.3.dist-info/METADATA
ColorDetect-1.6.3.dist-info/WHEEL
ColorDetect-1.6.3.dist-info/top_level.txt
ColorDetect-1.6.3.dist-info/RECORD
