Metadata-Version: 2.1
Name: ColorDetect
Version: 1.6.3
Summary: Detect and recognize colors in images or video
Home-page: https://github.com/MarvinKweyu/ColorDetect
Author: Marvin Kweyu
Author-email: mkweyu1@gmail.com
License: MIT
Classifier: Programming Language :: Python :: 3
Classifier: License :: OSI Approved :: MIT License
Classifier: Operating System :: POSIX :: Linux
Requires-Python: >=3.6
License-File: LICENSE
Requires-Dist: numpy>=1.18.1
Requires-Dist: matplotlib>=3.2.1
Requires-Dist: opencv-python>=4.2.0.32
Requires-Dist: scikit-learn>=0.22.2.post1
Requires-Dist: webcolors>=1.11.1
